LICENSE
MANIFEST.in
README.md
requirements.txt
setup.py
src/pii_decide/__init__.py
src/pii_decide/defs.py
src/pii_decide.egg-info/PKG-INFO
src/pii_decide.egg-info/SOURCES.txt
src/pii_decide.egg-info/dependency_links.txt
src/pii_decide.egg-info/entry_points.txt
src/pii_decide.egg-info/requires.txt
src/pii_decide.egg-info/top_level.txt
src/pii_decide/api/__init__.py
src/pii_decide/api/decider.py
src/pii_decide/app/__init__.py
src/pii_decide/app/decide.py
src/pii_decide/deciders/__init__.py
src/pii_decide/deciders/overlap_simple.py
src/pii_decide/helper/__init__.py
src/pii_decide/helper/misc.py